{
  "indexes": [
    {
      "collectionGroup": "wiki_pages",
      "queryScope": "COLLECTION",
      "fields": [
        { "fieldPath": "category", "order": "ASCENDING" },
        { "fieldPath": "updatedAt", "order": "DESCENDING" }
      ]
    },
    {
      "collectionGroup": "wiki_pages",
      "queryScope": "COLLECTION",
      "fields": [
        { "fieldPath": "tags", "arrayConfig": "CONTAINS" },
        { "fieldPath": "updatedAt", "order": "DESCENDING" }
      ]
    },
    {
      "collectionGroup": "wiki_pages",
      "queryScope": "COLLECTION",
      "fields": [
        { "fieldPath": "title", "order": "ASCENDING" }
      ]
    },
    {
      "collectionGroup": "wiki_recent_changes",
      "queryScope": "COLLECTION",
      "fields": [
        { "fieldPath": "editedAt", "order": "DESCENDING" }
      ]
    },
    {
      "collectionGroup": "revisions",
      "queryScope": "COLLECTION_GROUP",
      "fields": [
        { "fieldPath": "editedAt", "order": "DESCENDING" }
      ]
    }
  ],
  "fieldOverrides": []
}
